mysqlclient_pool.py
mysqlclient_pool-0.1.2.dist-info/LICENSE.md
mysqlclient_pool-0.1.2.dist-info/METADATA
mysqlclient_pool-0.1.2.dist-info/WHEEL
mysqlclient_pool-0.1.2.dist-info/top_level.txt
mysqlclient_pool-0.1.2.dist-info/RECORD
