Metadata-Version: 2.1
Name: mysqlclient-pool
Version: 0.1.2
Summary: MySQL database dynamic connection pool for 'mysqlclient' connector
Author-email: Saber Hayati <SaberHayati@outlook.com>
License: MIT License
Project-URL: homepage, https://github.com/Soberia/mysqlclient-pool
Keywords: mysqlclient,MySQLdb,database,connection pool
Classifier: Topic :: Database
Classifier: Programming Language :: Python
Classifier: Operating System :: OS Independent
Classifier: License :: OSI Approved :: MIT License
Requires-Python: >=3.10
License-File: LICENSE.md
Requires-Dist: mysqlclient
Provides-Extra: dev
Requires-Dist: build ; extra == 'dev'
Requires-Dist: black ; extra == 'dev'
